__init__.py
pysftptail.py
pysftptail_test.py
pysftptail-0.0.1.dist-info/AUTHORS.md
pysftptail-0.0.1.dist-info/LICENSE
pysftptail-0.0.1.dist-info/METADATA
pysftptail-0.0.1.dist-info/WHEEL
pysftptail-0.0.1.dist-info/dependency_links.txt
pysftptail-0.0.1.dist-info/entry_points.txt
pysftptail-0.0.1.dist-info/top_level.txt
pysftptail-0.0.1.dist-info/RECORD
