Metadata-Version: 2.1
Name: pysftptail
Version: 0.0.1
Summary: pySFTPtail is a Python3 implementaion of the tail command over a sftp connection
Home-page: https://github.com/tcvieira/pysftptail
Author: Thiago Vieira
Author-email: tcvieira@tcvieira.com
License: MIT
Download-URL: https://github.com/tcvieira/pysftptail/archive/0.0.1.tar.gz
Keywords: pysftp,sfpt,tail,logs
Platform: UNKNOWN
Classifier: License :: OSI Approved :: MIT License
Classifier: Programming Language :: Python :: 3.7
Requires-Python: >=3.7
Requires-Dist: click (==7.1.2)
Requires-Dist: paramiko (==2.7.1)
Requires-Dist: colorama (==0.4.3)
Requires-Dist: coverage (==5.2.1)
Requires-Dist: pytest (==6.0.1)
Requires-Dist: pytest-cov (==2.10.1)
Requires-Dist: pytest-sftpserver (==1.3.0)
Requires-Dist: twine (==3.2.0)
